resippy/__init__.py
resippy/image_objects/__init__.py
resippy/image_objects/abstract_image.py
resippy/image_objects/abstract_image_metadata.py
resippy/image_objects/image_factory.py
resippy/image_objects/earth_overhead/__init__.py
resippy/image_objects/earth_overhead/abstract_earth_overhead_image.py
resippy/image_objects/earth_overhead/digital_globe/DigitalGlobeImageFactory.py
resippy/image_objects/earth_overhead/digital_globe/__init__.py
resippy/image_objects/earth_overhead/digital_globe/view_ready_stereo/__init__.py
resippy/image_objects/earth_overhead/digital_globe/view_ready_stereo/view_ready_stereo_image.py
resippy/image_objects/earth_overhead/digital_globe/view_ready_stereo/view_ready_stereo_image_factory.py
resippy/image_objects/earth_overhead/digital_globe/view_ready_stereo/view_ready_stereo_metadata.py
resippy/image_objects/earth_overhead/digital_globe/view_ready_stereo/view_ready_stereo_point_calc.py
resippy/image_objects/earth_overhead/earth_overhead_point_calculators/__init__.py
resippy/image_objects/earth_overhead/earth_overhead_point_calculators/abstract_earth_overhead_point_calc.py
resippy/image_objects/earth_overhead/earth_overhead_point_calculators/earth_overhead_sensor_model.py
resippy/image_objects/earth_overhead/earth_overhead_point_calculators/fixtured_camera.py
resippy/image_objects/earth_overhead/earth_overhead_point_calculators/geotiff_point_calc.py
resippy/image_objects/earth_overhead/earth_overhead_point_calculators/ideal_pinhole_fpa_local_utm_point_calc.py
resippy/image_objects/earth_overhead/earth_overhead_point_calculators/opencv_point_calc.py
resippy/image_objects/earth_overhead/earth_overhead_point_calculators/pinhole_camera.py
resippy/image_objects/earth_overhead/earth_overhead_point_calculators/pix4d_point_calc.py
resippy/image_objects/earth_overhead/earth_overhead_point_calculators/rpc_point_calc.py
resippy/image_objects/earth_overhead/geotiff/__init__.py
resippy/image_objects/earth_overhead/geotiff/geotiff_image.py
resippy-0.3.0.dist-info/LICENSE
resippy-0.3.0.dist-info/METADATA
resippy-0.3.0.dist-info/WHEEL
resippy-0.3.0.dist-info/top_level.txt
resippy-0.3.0.dist-info/RECORD
