Metadata-Version: 2.1
Name: resippy
Version: 0.3.0
Summary: REmote Sensing and Image Processing in PYthon
Home-page: https://github.com/BeamIO-Inc/resippy
Author: BeamIO, Inc.
Author-email: info@beamio.net
License: BSD (3 clause)
Platform: UNKNOWN
Classifier: Programming Language :: Python :: 3
Classifier: License :: OSI Approved :: BSD License
Classifier: Operating System :: OS Independent
Requires-Dist: GDAL
Requires-Dist: pyproj
Requires-Dist: scipy
Requires-Dist: scikit-image
Requires-Dist: shapely
Requires-Dist: exifread
Requires-Dist: colorutils
Requires-Dist: imageio
Requires-Dist: numpy
Requires-Dist: scikit-learn
Requires-Dist: opencv-python
Requires-Dist: pint
Requires-Dist: seaborn
Requires-Dist: utm
